LICENSE
MANIFEST.in
README.rst
setup.cfg
setup.py
docs/Makefile
docs/conf.py
docs/index.rst
docs/make.bat
examples/baidu_news_spider.py
examples/single_spider.py
gspider/__init__.py
gspider/__main__.py
gspider/_patch.py
gspider/cmdline.py
gspider/commands.py
gspider/config.py
gspider/crawler.py
gspider/dupefilter.py
gspider/errors.py
gspider/eventbus.py
gspider/events.py
gspider/extension.py
gspider/fetcher.py
gspider/http.py
gspider/queue.py
gspider/run.py
gspider/selector.py
gspider/spider.py
gspider/utils.py
gspider.egg-info/PKG-INFO
gspider.egg-info/SOURCES.txt
gspider.egg-info/dependency_links.txt
gspider.egg-info/entry_points.txt
gspider.egg-info/not-zip-safe
gspider.egg-info/requires.txt
gspider.egg-info/top_level.txt
gspider/.idea/gspider.iml
gspider/.idea/misc.xml
gspider/.idea/modules.xml
gspider/.idea/vcs.xml
gspider/.idea/workspace.xml
gspider/extensions/__init__.py
gspider/extensions/depth.py
gspider/extensions/retry.py
requirements/docs.txt
requirements/selector.txt
requirements/test.txt
tests/__init__.py
tests/test_crawler.py
tests/test_fetcher.py