Metadata-Version: 2.1
Name: gspider
Version: 0.1.1
Summary: A web spider framework based on gevent and requests
Home-page: https://github.com/jadbin/gspider
Author: jadbin
Author-email: jadbin.com@hotmail.com
License: Apache 2
Platform: UNKNOWN
Classifier: License :: OSI Approved :: Apache Software License
Classifier: Intended Audience :: Developers
Classifier: Programming Language :: Python
Classifier: Programming Language :: Python :: 3
Classifier: Programming Language :: Python :: 3.6
Classifier: Topic :: Internet :: WWW/HTTP
Classifier: Topic :: Software Development :: Libraries :: Application Frameworks
Requires-Python: >=3.6
Provides-Extra: selector
